tigre/__init__.py
tigre/clean.py
tigre/clean_gdt.py
tigre/cli.py
tigre/combine.py
tigre/gff3_utils.py
tigre/igr.py
tigre/log_setup.py
tigre/py.typed
tigre/fasta_utils/__init__.py
tigre/fasta_utils/bedtools_wrapper.py
tigre/fasta_utils/biopython_wrapper.py
tigre-1.0.1.dist-info/METADATA
tigre-1.0.1.dist-info/WHEEL
tigre-1.0.1.dist-info/entry_points.txt
tigre-1.0.1.dist-info/licenses/LICENSE
tigre-1.0.1.dist-info/RECORD
