Metadata-Version: 2.4
Name: tigre
Version: 1.0.1
Summary: tigre - Tool for InterGenic Region Extraction
Project-URL: Homepage, https://github.com/brenodupin/tigre
Project-URL: Source, https://github.com/brenodupin/tigre
Author-email: Breno Dupin <breno.dupin@gmail.com>, Matheus Sanita Lima <msanital@uwo.ca>
License-Expression: MIT
License-File: LICENSE
Requires-Python: >=3.12
Requires-Dist: pandas<3.0.0,>=1.5.3
Provides-Extra: all
Requires-Dist: biopython>=1.80; extra == 'all'
Requires-Dist: gdt>=1.1.3; extra == 'all'
Provides-Extra: bio
Requires-Dist: biopython>=1.80; extra == 'bio'
Provides-Extra: gdt
Requires-Dist: gdt>=1.1.3; extra == 'gdt'
